fortpyx/__init__.py
fortpyx/error/__init__.py
fortpyx/error/fortnox_error.py
fortpyx/fortpyx.py
fortpyx/model/__init__.py
fortpyx/model/model.py
fortpyx/model/model_base.py
fortpyx/util/__init__.py
fortpyx/util/get_tokens.py
fortpyx-0.0.1a1.dist-info/LICENSE.md
fortpyx-0.0.1a1.dist-info/METADATA
fortpyx-0.0.1a1.dist-info/WHEEL
fortpyx-0.0.1a1.dist-info/RECORD
