Metadata-Version: 2.1
Name: fortpyx
Version: 0.0.1a1
Summary: Fully typed Fortnox SDK for Fortnox API v3.
License: MIT
Author: Robin Henriksson Törnström
Author-email: robin.henriksson@nortic.se
Requires-Python: >=3.9,<4.0
Classifier: License :: OSI Approved :: MIT License
Classifier: Programming Language :: Python :: 3
Classifier: Programming Language :: Python :: 3.9
Classifier: Programming Language :: Python :: 3.10
Classifier: Programming Language :: Python :: 3.11
Requires-Dist: pydantic (==2.7.1)
Requires-Dist: requests (==2.31.0)
Requires-Dist: types-requests (==2.31.0.20240406)
